ccfit2/__init__.py
ccfit2/__version__.py
ccfit2/ac.py
ccfit2/cli.py
ccfit2/dc.py
ccfit2/gui.py
ccfit2/relaxation.py
ccfit2/stats.py
ccfit2/utils.py
ccfit2/waveform.py
ccfit2/scripts/__init__.py
ccfit2/scripts/split_rates.py
ccfit2/scripts/update_ac_dc_params.py
ccfit2-5.12.4.dist-info/licenses/LICENSE
ccfit2-5.12.4.dist-info/METADATA
ccfit2-5.12.4.dist-info/WHEEL
ccfit2-5.12.4.dist-info/entry_points.txt
ccfit2-5.12.4.dist-info/top_level.txt
ccfit2-5.12.4.dist-info/RECORD
