Metadata-Version: 2.4
Name: ccfit2
Version: 5.12.4
Summary: CCFIT2 is a program for fitting AC and DC magnetisation data
Home-page: https://gitlab.com/chilton-group/cc-fit2
Project-URL: Bug Tracker, https://gitlab.com/chilton-group/cc-fit2/-/issues
Project-URL: Documentation, https://chilton-group.gitlab.io/cc-fit2
Classifier: Programming Language :: Python :: 3
Classifier: License :: OSI Approved :: GNU General Public License v3 (GPLv3)
Classifier: Operating System :: OS Independent
Requires-Python: >=3.10
License-File: LICENSE
Requires-Dist: numpy>=2.1.0
Requires-Dist: scipy>=1.14.1
Requires-Dist: matplotlib>=3.9.2
Requires-Dist: pillow>=10.4.0
Requires-Dist: qtpy>=2.4.1
Requires-Dist: pyqtgraph>=0.13.7
Requires-Dist: charset_normalizer>=3.3.2
Requires-Dist: pandas>=2.2.2
Dynamic: classifier
Dynamic: description
Dynamic: description-content-type
Dynamic: home-page
Dynamic: license-file
Dynamic: project-url
Dynamic: requires-dist
Dynamic: requires-python
Dynamic: summary
